weak_instruments/__init__.py
weak_instruments/anderson_rubin.py
weak_instruments/cjive.py
weak_instruments/data.csv
weak_instruments/data_gen.py
weak_instruments/hful.py
weak_instruments/ijive.py
weak_instruments/jive1.py
weak_instruments/jive2.py
weak_instruments/lagrange_multiplier.py
weak_instruments/lim_et_al.py
weak_instruments/liml.py
weak_instruments/monte_carlo.ipynb
weak_instruments/pre_test.py
weak_instruments/sjive.py
weak_instruments/test_jive.py
weak_instruments/tsls.py
weak_instruments/ujive1.py
weak_instruments/ujive2.py
weak_instruments-0.1.2.dist-info/METADATA
weak_instruments-0.1.2.dist-info/WHEEL
weak_instruments-0.1.2.dist-info/licenses/LICENSE
weak_instruments-0.1.2.dist-info/RECORD
