Metadata-Version: 2.4
Name: weak_instruments
Version: 0.1.2
Summary: A package for weak instruments in an instrumental variables regression.
Project-URL: Homepage, https://github.com/pypa/weak_instruments
Project-URL: Issues, https://github.com/pypa/weak_instruments/issues
Author-email: Jonathan Hyatt <hyatt.jonathan99@gmail.com>, Jacob Hutchings <jacobhutchings1@gmail.com>
License-Expression: MIT
License-File: LICENSE
Classifier: Operating System :: OS Independent
Classifier: Programming Language :: Python :: 3
Requires-Python: >=3.8
